JSONLibrary/JSONLibraryKeywords.py
JSONLibrary/__init__.py
JSONLibrary/version.py
robotframework_jsonlibrary-0.1.dist-info/top_level.txt
robotframework_jsonlibrary-0.1.dist-info/METADATA
robotframework_jsonlibrary-0.1.dist-info/DESCRIPTION.rst
robotframework_jsonlibrary-0.1.dist-info/metadata.json
robotframework_jsonlibrary-0.1.dist-info/WHEEL
robotframework_jsonlibrary-0.1.dist-info/RECORD
