Metadata-Version: 2.0
Name: robotframework-jsonlibrary
Version: 0.1
Summary: robotframework json jsonpath
Home-page: https://github.com/nottyo/robotframework-jsonlibrary.git
Author: Traitanit Huangsri
Author-email: traitanit.hua@gmail.com
License: UNKNOWN
Keywords: robotframework-jsonlibrary
Platform: UNKNOWN
Classifier: Development Status :: 5 - Production/Stable
Classifier: License :: Public Domain
Classifier: Operating System :: OS Independent
Classifier: Programming Language :: Python
Classifier: Topic :: Software Development :: Testing
Requires-Dist: tox
Requires-Dist: coverage
Requires-Dist: robotframework (>=3.0)
Requires-Dist: jsonpath-rw (==1.4.0)
